{
  "project_info": {
    "project_number": "503552610366",
    "project_id": "hexpresso-5d0d6",
    "storage_bucket": "hexpresso-5d0d6.firebasestorage.app"
  },
  "client": [
    {
      "client_info": {
        "mobilesdk_app_id": "1:503552610366:android:cc1f716cbeccc86186816f",
        "android_client_info": {
          "package_name": "com.faruktutkus.hexpresso"
        }
      },
      "oauth_client": [
        {
          "client_id": "503552610366-h2s9imrfccpuh0n653d0g9hl2gflehhf.apps.googleusercontent.com",
          "client_type": 1,
          "android_info": {
            "package_name": "com.faruktutkus.hexpresso",
            "certificate_hash": "96f5aaab0b80b37876b44c0ae47a4a6b0a26dd02"
          }
        },
        {
          "client_id": "503552610366-litquktjq3f0rhfug7qtblt61ks6jubc.apps.googleusercontent.com",
          "client_type": 1,
          "android_info": {
            "package_name": "com.faruktutkus.hexpresso",
            "certificate_hash": "5e8f16062ea3cd2c4a0d547876baa6f38cabf625"
          }
        },
        {
          "client_id": "503552610366-si1i5n92s4p23v912vpkfk6dt43c6usc.apps.googleusercontent.com",
          "client_type": 1,
          "android_info": {
            "package_name": "com.faruktutkus.hexpresso",
            "certificate_hash": "7ccdc673556c80da2722d5f530b528c336135342"
          }
        },
        {
          "client_id": "503552610366-ul10rk2bvmt9c2ujfsvc1l38bro150un.apps.googleusercontent.com",
          "client_type": 1,
          "android_info": {
            "package_name": "com.faruktutkus.hexpresso",
            "certificate_hash": "6aa2a3cc5e2c76497b385a7b313e5894091170f4"
          }
        },
        {
          "client_id": "503552610366-cncgkggphfoi53jna1euf5qsmpnl46oe.apps.googleusercontent.com",
          "client_type": 3
        }
      ],
      "api_key": [
        {
          "current_key": "AIzaSyAwFNpbt-ZzfqEAKokSqU9-ozeOnhpq43o"
        }
      ],
      "services": {
        "appinvite_service": {
          "other_platform_oauth_client": [
            {
              "client_id": "503552610366-cncgkggphfoi53jna1euf5qsmpnl46oe.apps.googleusercontent.com",
              "client_type": 3
            }
          ]
        }
      },
      "admob_app_id": "ca-app-pub-2363017162977044~8550998696"
    }
  ],
  "configuration_version": "1"
}